{
  "db_name": "PostgreSQL",
  "query": "\n        SELECT\n            id,\n            election_id,\n            payload,\n            certificate,\n            signature\n        FROM objects\n        WHERE id = $1\n        ",
  "describe": {
    "columns": [
      {
        "ordinal": 0,
        "name": "id",
        "type_info": "Uuid"
      },
      {
        "ordinal": 1,
        "name": "election_id",
        "type_info": "Uuid"
      },
      {
        "ordinal": 2,
        "name": "payload",
        "type_info": "Bytea"
      },
      {
        "ordinal": 3,
        "name": "certificate",
        "type_info": "Bytea"
      },
      {
        "ordinal": 4,
        "name": "signature",
        "type_info": "Bytea"
      }
    ],
    "parameters": {
      "Left": [
        "Uuid"
      ]
    },
    "nullable": [
      false,
      true,
      false,
      false,
      false
    ]
  },
  "hash": "810bde68dba12004e18f64699de0528a72b96cf549bd107f8268ad1db98b25ed"
}
